{"athlete": "Usain BOLT", "event": "\r\n                    Men's 100m", "result": "9.63"}
{"athlete": "Yohan BLAKE", "event": "\r\n                    Men's 100m", "result": "9.75"}
{"athlete": "Justin GATLIN", "event": "\r\n                    Men's 100m", "result": "9.79"}
{"athlete": "Usain BOLT", "event": "\r\n                    Men's 200m", "result": "19.32"}
{"athlete": "Yohan BLAKE", "event": "\r\n                    Men's 200m", "result": "19.44"}
{"athlete": "Warren WEIR", "event": "\r\n                    Men's 200m", "result": "19.84"}
{"athlete": "Kirani JAMES", "event": "\r\n                    Men's 400m", "result": "43.94"}
{"athlete": "Luguelin SANTOS", "event": "\r\n                    Men's 400m", "result": "44.46"}
{"athlete": "Lalonde GORDON", "event": "\r\n                    Men's 400m", "result": "44.52"}
{"athlete": "David Lekuta RUDISHA", "event": "\r\n                    Men's 800m", "result": "1:40.91"}
{"athlete": "Nijel AMOS", "event": "\r\n                    Men's 800m", "result": "1:41.73"}
{"athlete": "Timothy KITUM", "event": "\r\n                    Men's 800m", "result": "1:42.53"}
{"athlete": "Aries MERRITT", "event": "\r\n                    Men's 110m Hurdles", "result": "12.92"}
{"athlete": "Jason RICHARDSON", "event": "\r\n                    Men's 110m Hurdles", "result": "13.04"}
{"athlete": "Hansle PARCHMENT", "event": "\r\n                    Men's 110m Hurdles", "result": "13.12"}
{"athlete": "Taoufik MAKHLOUFI", "event": "\r\n                    Men's 1500m", "result": "3:34.08"}
{"athlete": "Leonel MANZANO", "event": "\r\n                    Men's 1500m", "result": "3:34.79"}
{"athlete": "Abdalaati IGUIDER", "event": "\r\n                    Men's 1500m", "result": "3:35.13"}
{"athlete": "Ezekiel KEMBOI", "event": "\r\n                    Men's 3000m Steeplechase", "result": "8:18.56"}
{"athlete": "Usain BOLT", "event": "\r\n                    Men's 100m", "result": "9.69"}
{"athlete": "Mahiedine MEKHISSI-BENABBAD", "event": "\r\n                    Men's 3000m Steeplechase", "result": "8:19.08"}
{"athlete": "Abel Kiprop MUTAI", "event": "\r\n                    Men's 3000m Steeplechase", "result": "8:19.73"}
{"athlete": "Felix SANCHEZ", "event": "\r\n                    Men's 400m Hurdles", "result": "47.63"}
{"athlete": "Michael TINSLEY", "event": "\r\n                    Men's 400m Hurdles", "result": "47.91"}
{"athlete": "Richard THOMPSON", "event": "\r\n                    Men's 100m", "result": "9.89"}
{"athlete": "Walter DIX", "event": "\r\n                    Men's 100m", "result": "9.91"}
{"athlete": "Usain BOLT", "event": "\r\n                    Men's 200m", "result": "19.30"}
{"athlete": "Shawn CRAWFORD", "event": "\r\n                    Men's 200m", "result": "19.96"}
{"athlete": "Walter DIX", "event": "\r\n                    Men's 200m", "result": "19.98"}
{"athlete": "LaShawn MERRITT", "event": "\r\n                    Men's 400m", "result": "43.75"}
{"athlete": "Javier CULSON", "event": "\r\n                    Men's 400m Hurdles", "result": "48.10"}
{"athlete": "Mo FARAH", "event": "\r\n                    Men's 5000m", "result": "13:41.66"}
{"athlete": "Dejen GEBREMESKEL", "event": "\r\n                    Men's 5000m", "result": "13:41.98"}
{"athlete": "Thomas Pkemei LONGOSIWA", "event": "\r\n                    Men's 5000m", "result": "13:42.36"}
{"athlete": "Jeremy WARINER", "event": "\r\n                    Men's 400m", "result": "44.74"}
{"athlete": "David NEVILLE", "event": "\r\n                    Men's 400m", "result": "44.80"}
{"athlete": "Wilfred BUNGEI", "event": "\r\n                    Men's 800m", "result": "1:44.65"}
{"athlete": "Ismail Ahmed ISMAIL", "event": "\r\n                    Men's 800m", "result": "1:44.70"}
{"athlete": "Alfred Kirwa YEGO", "event": "\r\n                    Men's 800m", "result": "1:44.82"}
{"athlete": "Dayron ROBLES", "event": "\r\n                    Men's 110m Hurdles", "result": "12.93"}
{"athlete": "Tomasz MAJEWSKI", "event": "\r\n                    Men's Shot Put", "result": "21.89"}
{"athlete": "David STORL", "event": "\r\n                    Men's Shot Put", "result": "21.86"}
{"athlete": "Reese HOFFA", "event": "\r\n                    Men's Shot Put", "result": "21.23"}
{"athlete": "Robert HARTING", "event": "\r\n                    Men's Discus Throw", "result": "68.27"}
{"athlete": "David PAYNE", "event": "\r\n                    Men's 110m Hurdles", "result": "13.17"}
{"athlete": "David OLIVER", "event": "\r\n                    Men's 110m Hurdles", "result": "13.18"}
{"athlete": "Asbel Kipruto KIPROP", "event": "\r\n                    Men's 1500m", "result": "3:33.11"}
{"athlete": "Nicholas WILLIS", "event": "\r\n                    Men's 1500m", "result": "3:34.16"}
{"athlete": "Ehsan HADADI", "event": "\r\n                    Men's Discus Throw", "result": "68.18"}
{"athlete": "Gerd KANTER", "event": "\r\n                    Men's Discus Throw", "result": "68.03"}
{"athlete": "Keshorn WALCOTT", "event": "\r\n                    Men's Javelin Throw", "result": "84.58"}
{"athlete": "Oleksandr PYATNYTSYA", "event": "\r\n                    Men's Javelin Throw", "result": "84.51"}
{"athlete": "Antti RUUSKANEN", "event": "\r\n                    Men's Javelin Throw", "result": "84.12"}
{"athlete": "Medhi BAALA", "event": "\r\n                    Men's 1500m", "result": "3:34.21"}
{"athlete": "Brimin Kiprop KIPRUTO", "event": "\r\n                    Men's 3000m Steeplechase", "result": "8:10.34"}
{"athlete": "Mahiedine MEKHISSI-BENABBAD", "event": "\r\n                    Men's 3000m Steeplechase", "result": "8:10.49"}
{"athlete": "Richard Kipkemboi MATEELONG", "event": "\r\n                    Men's 3000m Steeplechase", "result": "8:11.01"}
{"athlete": "Angelo TAYLOR", "event": "\r\n                    Men's 400m Hurdles", "result": "47.25"}
{"athlete": "Krisztian PARS", "event": "\r\n                    Men's Hammer Throw", "result": "80.59"}
{"athlete": "Primoz KOZMUS", "event": "\r\n                    Men's Hammer Throw", "result": "79.36"}
{"athlete": "Koji MUROFUSHI", "event": "\r\n                    Men's Hammer Throw", "result": "78.71"}
{"athlete": "Greg RUTHERFORD", "event": "\r\n                    Men's Long Jump", "result": "8.31"}
{"athlete": "Kerron CLEMENT", "event": "\r\n                    Men's 400m Hurdles", "result": "47.98"}
{"athlete": "Bershawn JACKSON", "event": "\r\n                    Men's 400m Hurdles", "result": "48.06"}
{"athlete": "Kenenisa BEKELE", "event": "\r\n                    Men's 5000m", "result": "12:57.82"}
{"athlete": "Eliud Kipchoge ROTICH", "event": "\r\n                    Men's 5000m", "result": "13:02.80"}
{"athlete": "Edwin Cheruiyot SOI", "event": "\r\n                    Men's 5000m", "result": "13:06.22"}
{"athlete": "Mitchell WATT", "event": "\r\n                    Men's Long Jump", "result": "8.16"}
{"athlete": "Will CLAYE", "event": "\r\n                    Men's Long Jump", "result": "8.12"}
{"athlete": "Christian TAYLOR", "event": "\r\n                    Men's Triple Jump", "result": "17.81"}
{"athlete": "Tomasz MAJEWSKI", "event": "\r\n                    Men's Shot Put", "result": "21.51"}
{"athlete": "Christian CANTWELL", "event": "\r\n                    Men's Shot Put", "result": "21.09"}
{"athlete": "Dylan ARMSTRONG", "event": "\r\n                    Men's Shot Put", "result": "21.04"}
{"athlete": "Gerd KANTER", "event": "\r\n                    Men's Discus Throw", "result": "68.82"}
{"athlete": "Will CLAYE", "event": "\r\n                    Men's Triple Jump", "result": "17.62"}
{"athlete": "Fabrizio DONATO", "event": "\r\n                    Men's Triple Jump", "result": "17.48"}
{"athlete": "Ivan UKHOV", "event": "\r\n                    Men's High Jump", "result": "2.38"}
{"athlete": "Piotr MALACHOWSKI", "event": "\r\n                    Men's Discus Throw", "result": "67.82"}
{"athlete": "Virgilijus ALEKNA", "event": "\r\n                    Men's Discus Throw", "result": "67.79"}
{"athlete": "Andreas THORKILDSEN", "event": "\r\n                    Men's Javelin Throw", "result": "90.57"}
{"athlete": "Ainars KOVALS", "event": "\r\n                    Men's Javelin Throw", "result": "86.64"}
{"athlete": "Tero PITKAMAKI", "event": "\r\n                    Men's Javelin Throw", "result": "86.16"}
{"athlete": "Erik KYNARD", "event": "\r\n                    Men's High Jump", "result": "2.33"}
{"athlete": "Mutaz Essa BARSHIM", "event": "\r\n                    Men's High Jump", "result": "2.29"}
{"athlete": "Derek DROUIN", "event": "\r\n                    Men's High Jump", "result": "2.29"}
{"athlete": "Robert GRABARZ", "event": "\r\n                    Men's High Jump", "result": "2.29"}
{"athlete": "Renaud LAVILLENIE", "event": "\r\n                    Men's Pole Vault", "result": "5.97"}
{"athlete": "Primoz KOZMUS", "event": "\r\n                    Men's Hammer Throw", "result": "82.02"}
{"athlete": "Vadim DEVYATOVSKIY", "event": "\r\n                    Men's Hammer Throw", "result": "81.61"}
{"athlete": "Ivan TSIKHAN", "event": "\r\n                    Men's Hammer Throw", "result": "81.51"}
{"athlete": "Irving SALADINO", "event": "\r\n                    Men's Long Jump", "result": "8.34"}
{"athlete": "Bjorn OTTO", "event": "\r\n                    Men's Pole Vault", "result": "5.91"}
{"athlete": "Raphael HOLZDEPPE", "event": "\r\n                    Men's Pole Vault", "result": "5.91"}
{"athlete": "Ding CHEN", "event": "\r\n                    Men's 20km Walk", "result": "1:18:46"}
{"athlete": "Godfrey Khotso MOKOENA", "event": "\r\n                    Men's Long Jump", "result": "8.24"}
{"athlete": "Ibrahim CAMEJO", "event": "\r\n                    Men's Long Jump", "result": "8.20"}
{"athlete": "Nelson EVORA", "event": "\r\n                    Men's Triple Jump", "result": "17.67"}
{"athlete": "Erick BARRONDO", "event": "\r\n                    Men's 20km Walk", "result": "1:18:57"}
{"athlete": "Zhen WANG", "event": "\r\n                    Men's 20km Walk", "result": "1:19:25"}
{"athlete": "Sergey KIRDYAPKIN", "event": "\r\n                    Men's 50km Walk", "result": "3:35:59"}
{"athlete": "Phillips IDOWU", "event": "\r\n                    Men's Triple Jump", "result": "17.62"}
{"athlete": "Leevan SANDS", "event": "\r\n                    Men's Triple Jump", "result": "17.59"}
{"athlete": "Andrey SILNOV", "event": "\r\n                    Men's High Jump", "result": "2.36"}
{"athlete": "Jared TALLENT", "event": "\r\n                    Men's 50km Walk", "result": "3:36:53"}
{"athlete": "Tianfeng SI", "event": "\r\n                    Men's 50km Walk", "result": "3:37:16"}
{"athlete": "Stephen KIPROTICH", "event": "\r\n                    Men's Marathon", "result": "2:08:01"}
{"athlete": "Germaine MASON", "event": "\r\n                    Men's High Jump", "result": "2.34"}
{"athlete": "Yaroslav RYBAKOV", "event": "\r\n                    Men's High Jump", "result": "2.34"}
{"athlete": "Steve HOOKER", "event": "\r\n                    Men's Pole Vault", "result": "5.96"}
{"athlete": "Abel KIRUI", "event": "\r\n                    Men's Marathon", "result": "2:08:27"}
{"athlete": "Wilson Kipsang KIPROTICH", "event": "\r\n                    Men's Marathon", "result": "2:09:37"}
{"athlete": "Mo FARAH", "event": "\r\n                    Men's 10000m", "result": "27:30.42"}
{"athlete": "Evgeniy LUKYANENKO", "event": "\r\n                    Men's Pole Vault", "result": "5.85"}
{"athlete": "Denys YURCHENKO", "event": "\r\n                    Men's Pole Vault", "result": "5.70"}
{"athlete": "Valeriy BORCHIN", "event": "\r\n                    Men's 20km Walk", "result": "1h19:01"}
{"athlete": "Jefferson PEREZ", "event": "\r\n                    Men's 20km Walk", "result": "1h19:15"}
{"athlete": "Galen RUPP", "event": "\r\n                    Men's 10000m", "result": "27:30.90"}
{"athlete": "Tariku BEKELE", "event": "\r\n                    Men's 10000m", "result": "27:31.43"}
{"athlete": " JAMAICA", "event": "\r\n                    Men's 4x100m Relay", "result": "36.84"}
{"athlete": "Jared TALLENT", "event": "\r\n                    Men's 20km Walk", "result": "1h19:42"}
{"athlete": "Alex SCHWAZER", "event": "\r\n                    Men's 50km Walk", "result": "3h37:09"}
{"athlete": " UNITED STATES OF AMERICA", "event": "\r\n                    Men's 4x100m Relay", "result": "37.04"}
{"athlete": " TRINIDAD AND TOBAGO", "event": "\r\n                    Men's 4x100m Relay", "result": "38.12"}
{"athlete": " BAHAMAS", "event": "\r\n                    Men's 4x400m Relay", "result": "2:56.72"}
{"athlete": "Jared TALLENT", "event": "\r\n                    Men's 50km Walk", "result": "3h39:27"}
{"athlete": "Denis NIZHEGORODOV", "event": "\r\n                    Men's 50km Walk", "result": "3h40:14"}
{"athlete": "Samuel Kamau WANSIRU", "event": "\r\n                    Men's Marathon", "result": "2h06:32"}
{"athlete": " UNITED STATES OF AMERICA", "event": "\r\n                    Men's 4x400m Relay", "result": "2:57.05"}
{"athlete": " TRINIDAD AND TOBAGO", "event": "\r\n                    Men's 4x400m Relay", "result": "2:59.40"}
{"athlete": "Ashton EATON", "event": "\r\n                    Men's Decathlon", "result": "8869"}
{"athlete": "Jaouad GHARIB", "event": "\r\n                    Men's Marathon", "result": "2h07:16"}
{"athlete": "Tsegay KEBEDE", "event": "\r\n                    Men's Marathon", "result": "2h10:00"}
{"athlete": "Kenenisa BEKELE", "event": "\r\n                    Men's 10000m", "result": "27:01.17"}
{"athlete": "Trey HARDEE", "event": "\r\n                    Men's Decathlon", "result": "8671"}
{"athlete": "Leonel SUAREZ", "event": "\r\n                    Men's Decathlon", "result": "8523"}
{"athlete": "Sileshi SIHINE", "event": "\r\n                    Men's 10000m", "result": "27:02.77"}
{"athlete": "Micah KOGO", "event": "\r\n                    Men's 10000m", "result": "27:04.11"}
{"athlete": "Jamaica", "event": "\r\n                    Men's 4x100m Relay", "result": "37.10"}
{"athlete": "Trinidad and Tobago", "event": "\r\n                    Men's 4x100m Relay", "result": "38.06"}
{"athlete": "Japan", "event": "\r\n                    Men's 4x100m Relay", "result": "38.15"}
{"athlete": "United States of America", "event": "\r\n                    Men's 4x400m Relay", "result": "2:55.39"}
{"athlete": "Bahamas", "event": "\r\n                    Men's 4x400m Relay", "result": "2:58.03"}
{"athlete": "Russian Federation", "event": "\r\n                    Men's 4x400m Relay", "result": "2:58.06"}
{"athlete": "Bryan CLAY", "event": "\r\n                    Men's Decathlon", "result": "8791"}
{"athlete": "Andrei KRAUCHANKA", "event": "\r\n                    Men's Decathlon", "result": "8551"}
{"athlete": "Leonel SUAREZ", "event": "\r\n                    Men's Decathlon", "result": "8527"}
